CHANGELOG.md
LICENSE.md
README.md
TODO.md
setup.py
doc/legtest.py
doc/legtest2.py
doc/legtest3.py
doc/pydgq_user_manual.lyx
doc/pydgq_user_manual.pdf
pydgq/__init__.py
pydgq/pydgq_data_27.bin
pydgq/pydgq_data_34.bin
pydgq.egg-info/PKG-INFO
pydgq.egg-info/SOURCES.txt
pydgq.egg-info/dependency_links.txt
pydgq.egg-info/not-zip-safe
pydgq.egg-info/requires.txt
pydgq.egg-info/top_level.txt
pydgq/solver/__init__.py
pydgq/solver/builtin_kernels.c
pydgq/solver/builtin_kernels.pxd
pydgq/solver/builtin_kernels.pyx
pydgq/solver/cminmax.pxd
pydgq/solver/compsum.c
pydgq/solver/compsum.pxd
pydgq/solver/compsum.pyx
pydgq/solver/explicit.c
pydgq/solver/explicit.pxd
pydgq/solver/explicit.pyx
pydgq/solver/fputils.pxd
pydgq/solver/galerkin.c
pydgq/solver/galerkin.pxd
pydgq/solver/galerkin.pyx
pydgq/solver/implicit.c
pydgq/solver/implicit.pxd
pydgq/solver/implicit.pyx
pydgq/solver/integrator_interface.c
pydgq/solver/integrator_interface.pxd
pydgq/solver/integrator_interface.pyx
pydgq/solver/kernel_interface.c
pydgq/solver/kernel_interface.pxd
pydgq/solver/kernel_interface.pyx
pydgq/solver/odesolve.c
pydgq/solver/odesolve.pyx
pydgq/solver/pydgq_types.c
pydgq/solver/types.c
pydgq/solver/types.pxd
pydgq/solver/types.pyx
pydgq/utils/__init__.py
pydgq/utils/discontify.c
pydgq/utils/discontify.pyx
pydgq/utils/listutils.py
pydgq/utils/mpi_shim.py
pydgq/utils/precalc.py
test/builtin_1storder_kernel_test.py
test/builtin_1storder_withmass_kernel_test.py
test/builtin_2ndorder_kernel_test.py
test/builtin_2ndorder_withmass_kernel_test.py
test/cython_kernel.c
test/cython_kernel.pxd
test/cython_kernel.pyx
test/cython_kernel.so
test/cython_kernel_test.py
test/lorenz_example.py
test/python_kernel_test.py
test/runtests2.sh
test/runtests3.sh
test/setup.py