Metadata-Version: 1.1
Name: pydgq
Version: 0.1.2
Summary: ODE system solver using dG(q) (time-discontinuous Galerkin w/ Lobatto basis)
Home-page: https://github.com/Technologicat/pydgq
Author: Juha Jeronen
Author-email: juha.jeronen@jyu.fi
License: BSD
Keywords: numerical integration ordinary-differential-equations ode ivp ode-solver solver galerkin discontinuous-galerkin cython numpy
Platform: Linux
Classifier: Development Status :: 4 - Beta
Classifier: Environment :: Console
Classifier: Intended Audience :: Developers
Classifier: Intended Audience :: Science/Research
Classifier: License :: OSI Approved :: BSD License
Classifier: Operating System :: POSIX :: Linux
Classifier: Programming Language :: Cython
Classifier: Programming Language :: Python
Classifier: Programming Language :: Python :: 2
Classifier: Programming Language :: Python :: 2.7
Classifier: Programming Language :: Python :: 3
Classifier: Programming Language :: Python :: 3.4
Classifier: Topic :: Scientific/Engineering
Classifier: Topic :: Scientific/Engineering :: Mathematics
Classifier: Topic :: Software Development :: Libraries
Classifier: Topic :: Software Development :: Libraries :: Python Modules
Provides: pydgq
